chzzkpy/__init__.py
chzzkpy/authorization.py
chzzkpy/base_model.py
chzzkpy/category.py
chzzkpy/channel.py
chzzkpy/chat.py
chzzkpy/client.py
chzzkpy/enums.py
chzzkpy/error.py
chzzkpy/flags.py
chzzkpy/gateway.py
chzzkpy/http.py
chzzkpy/live.py
chzzkpy/message.py
chzzkpy/oauth2.py
chzzkpy/packet.py
chzzkpy/payload.py
chzzkpy/restriction.py
chzzkpy/session.py
chzzkpy/state.py
chzzkpy/unofficial/__init__.py
chzzkpy/unofficial/base_model.py
chzzkpy/unofficial/channel.py
chzzkpy/unofficial/client.py
chzzkpy/unofficial/error.py
chzzkpy/unofficial/http.py
chzzkpy/unofficial/live.py
chzzkpy/unofficial/search.py
chzzkpy/unofficial/user.py
chzzkpy/unofficial/video.py
chzzkpy/unofficial/chat/__init__.py
chzzkpy/unofficial/chat/access_token.py
chzzkpy/unofficial/chat/blind.py
chzzkpy/unofficial/chat/chat_client.py
chzzkpy/unofficial/chat/connected.py
chzzkpy/unofficial/chat/donation.py
chzzkpy/unofficial/chat/enums.py
chzzkpy/unofficial/chat/error.py
chzzkpy/unofficial/chat/gateway.py
chzzkpy/unofficial/chat/http.py
chzzkpy/unofficial/chat/message.py
chzzkpy/unofficial/chat/profile.py
chzzkpy/unofficial/chat/recent_chat.py
chzzkpy/unofficial/chat/state.py
chzzkpy/unofficial/manage/__init__.py
chzzkpy/unofficial/manage/chat_activity_count.py
chzzkpy/unofficial/manage/chat_rule.py
chzzkpy/unofficial/manage/enums.py
chzzkpy/unofficial/manage/http.py
chzzkpy/unofficial/manage/manage_client.py
chzzkpy/unofficial/manage/manage_search.py
chzzkpy/unofficial/manage/prohibit_word.py
chzzkpy/unofficial/manage/stream.py
chzzkpy-2.1.5.dist-info/licenses/LICENSE
chzzkpy-2.1.5.dist-info/METADATA
chzzkpy-2.1.5.dist-info/WHEEL
chzzkpy-2.1.5.dist-info/top_level.txt
chzzkpy-2.1.5.dist-info/RECORD
